README.md
setup.py
countybot_us/__init__.py
countybot_us/profile.py
countybot_us.egg-info/PKG-INFO
countybot_us.egg-info/SOURCES.txt
countybot_us.egg-info/dependency_links.txt
countybot_us.egg-info/entry_points.txt
countybot_us.egg-info/requires.txt
countybot_us.egg-info/top_level.txt