Metadata-Version: 2.1
Name: countybot-us
Version: 0.0.2
Summary: A Twitter bot built with munibot that tweets imagery of US Counties and equivalent units
Home-page: https://github.com/amercader/countybot_us
Author: Adrià Mercader
Author-email: amercadero@gmail.com
License: UNKNOWN
Platform: UNKNOWN
Classifier: Programming Language :: Python :: 3
Classifier: License :: OSI Approved :: MIT License
Classifier: Operating System :: OS Independent
Requires-Python: >=3.6
